buco_db_controller
