Metadata-Version: 2.1
Name: buco-db-controller
Version: 1.1.46
Requires-Dist: PyYAML
Requires-Dist: RapidFuzz
Requires-Dist: pymongo
Requires-Dist: dnspython
Requires-Dist: Unidecode
